do_dns_manager/__init__.py
do_dns_manager/__main__.py
do_dns_manager/app.py
do_dns_manager/htpasswd.py
do_dns_manager/main.py
do_dns_manager/templates/list.html
do_dns_manager-0.1.dist-info/DESCRIPTION.rst
do_dns_manager-0.1.dist-info/METADATA
do_dns_manager-0.1.dist-info/RECORD
do_dns_manager-0.1.dist-info/WHEEL
do_dns_manager-0.1.dist-info/entry_points.txt
do_dns_manager-0.1.dist-info/metadata.json
do_dns_manager-0.1.dist-info/top_level.txt
