Metadata-Version: 2.0
Name: do-dns-manager
Version: 0.1
Summary: A DNS record manager using DigitalOcean as backend, useful for assigning DNS records in a DHCP hook.
Home-page: https://github.com/quantum5/do-dns-manager
Author: Quantum
Author-email: quantum@dmoj.ca
License: UNKNOWN
Platform: UNKNOWN
Classifier: Development Status :: 3 - Alpha
Classifier: License :: OSI Approved :: GNU Affero General Public License v3 or later (AGPLv3+)
Classifier: Programming Language :: Python :: 3
Requires-Dist: tornado
Requires-Dist: tornado-http-auth
